setup.py
modulocator/__init__.py
modulocator.egg-info/PKG-INFO
modulocator.egg-info/SOURCES.txt
modulocator.egg-info/dependency_links.txt
modulocator.egg-info/entry_points.txt
modulocator.egg-info/top_level.txt