Metadata-Version: 1.1
Name: modulocator
Version: 0.0.2
Summary: A helper function for development of modules in jupyter notebook.
Home-page: https://github.com/draperjames/modulocator/
Author: James Draper
Author-email: james.draper@duke.edu
License: MIT
Keywords: Jupyter Notebook
Platform: UNKNOWN
Classifier: Development Status :: 3 - Alpha
Classifier: Intended Audience :: Developers
Classifier: Topic :: Software Development :: Build Tools
Classifier: License :: OSI Approved :: MIT License
Classifier: Programming Language :: Python :: 2
Classifier: Programming Language :: Python :: 2.6
Classifier: Programming Language :: Python :: 2.7
Classifier: Programming Language :: Python :: 3
Classifier: Programming Language :: Python :: 3.3
Classifier: Programming Language :: Python :: 3.4
Classifier: Programming Language :: Python :: 3.5
